{
"spider": "https://gh.jasonzeng.dev/https://raw.githubusercontent.com/wuheng18/zy/refs/heads/master/py/vox.jar",
    "sites": [
    {
            "key": "海狗视频",
            "name": "刘彬影视",
            "type": 3,
            "api": "csp_Hmys",
            "changeable": 0,
            "ext": {
                "host": "https://dy.stxbed.com",
                "app_id": "shiguang",
                "deviceid": "6b3927d7bbd112d6",
                "versionCode": "20000",
                "UMENG_CHANNEL": "guan"
            }
        },
        {
            "key": "白云视频",
            "name": "白云影视｜APP",
            "type": 3,
            "api": "csp_Hmys",
            "changeable": 0,
            "ext": {
                "host": "https://dy.oogsy.com",
                "app_id": "baiyun",
                "deviceid": "9904b2c2cec97ac1",
                "versionCode": "30000",
                "UMENG_CHANNEL": "semc07"
            }
        },
        {
            "key": "溏心视频",
            "name": "溏心影视｜APP",
            "type": 3,
            "api": "csp_Hmys",
            "changeable": 0,
            "ext": {
                "host": "https://dy.jszdzs.com",
                "app_id": "xuebao",
                "deviceid": "9904b2c2cec97ac1",
                "versionCode": "23000",
                "UMENG_CHANNEL": "zhuan"
            }
        },
        {
            "key": "呱呱视频",
            "name": "呱呱影视｜APP",
            "type": 3,
            "api": "csp_Hmys",
            "changeable": 0,
            "ext": {
                "host": "https://dy.zhiquw.com",
                "app_id": "guagua",
                "deviceid": "b0ea326d7a14820f",
                "versionCode": "10000",
                "UMENG_CHANNEL": "changfeng"
            }
        },
        {
            "key": "云野视频",
            "name": "云野影视｜APP",
            "type": 3,
            "api": "csp_Hmys",
            "changeable": 0,
            "ext": {
                "host": "https://dy.zhiquw.com",
                "app_id": "yunye",
                "deviceid": "9904b2c2cec97ac1",
                "versionCode": "10000",
                "UMENG_CHANNEL": "zhuan"
            }
        },
        {
            "key": "拾光视频",
            "name": "拾光影视｜APP",
            "type": 3,
            "api": "csp_Hmys",
            "changeable": 0,
            "ext": {
                "host": "https://dy.zhiquw.com",
                "app_id": "shiguang",
                "deviceid": "2712cc11e4f294b5",
                "versionCode": "10000",
                "UMENG_CHANNEL": "semc07"
            }
        },
        {
            "key": "花小猪APP",
            "name": "小猪影视｜APP",
            "type": 3,
            "searchable": 1,
            "changeable": 1,
            "api": "csp_AppGet",
            "ext": {
                "host": "https://tiantangyoulu.oss-cn-beijing.aliyuncs.com/tengxunyun.txt",
                "ua": "okhttp/3.10.0",
                "datakey": "seb5tq9mykp2w9ry",
                "api": 2
            }
        },
        {
            "key": "仓鼠",
            "name": "仓鼠影视｜APP",
            "type": 3,
            "searchable": 1,
            "changeable": 1,
            "api": "csp_AppGet",
            "ext": {
                "host": "https://ceshi307386.oss-cn-beijing.aliyuncs.com/ceshi421.txt",
                "datakey": "da61247f5b662597",
                "api": 2
            }
        },
        {
            "key": "麻花",
            "name": "麻花影视｜APP",
            "type": 3,
            "searchable": 1,
            "changeable": 1,
            "api": "csp_AppGet",
            "ext": {
                "host": "https://apicoss-alimama-com-1307821617.file.myqcloud.com/Uploadsget",
                "datakey": "q7gj4f9br3fls6nh"
            }
        },
        {
            "key": "萝卜",
            "name": "萝卜影视｜APP",
            "type": 3,
            "searchable": 1,
            "changeable": 1,
            "api": "csp_AppGet",
            "ext": {
                "host": "https://apiapplbys.lbys.app:5678",
                "datakey": "apiapplbyskey168"
            }
        },
        {
            "key": "灵虎",
            "name": "灵虎影视｜APP",
            "type": 3,
            "searchable": 1,
            "changeable": 1,
            "api": "csp_AppGet",
            "ext": {
                "host": "https://bind.315999.xyz/89.txt",
                "datakey": "#getapp@TMD@2025"
            }
        },
        {
            "key": "莱米",
            "name": "莱米影视｜APP",
            "type": 3,
            "searchable": 1,
            "changeable": 1,
            "api": "csp_AppGet",
            "ext": {
                "host": "http://laiget-1313189639.cos.ap-guangzhou.myqcloud.com/laimi.txt",
                "datakey": "ce032244d093b3e2"
            }
        },
        {
            "key": "小帅",
            "name": "小帅影视｜APP",
            "type": 3,
            "searchable": 1,
            "changeable": 1,
            "api": "csp_AppGet",
            "ext": {
                "host": "http://jcy.kfzy.org",
                "datakey": "672263e98f232a05"
            }
        },
        {
            "key": "欣欣影视",
            "name": "欣欣影视｜APP",
            "type": 3,
            "api": "https://raw.githubusercontent.com/wuheng18/zy/refs/heads/master/py/XinJie.py",
            "ext": {
                "host": "usv46c9uRCE/PugcvJY1Pc/BM6KQv8vKYzpgVFmTPv8wdb18jQRMx9ElUPtnlHCd",
                "key": "505cab36b1111416",
                "iv": "0e832063ac451b27"
            }
        },
        {
            "key": "鲸鱼影视",
            "name": "鲸鱼影视｜App",
            "type": 3,
            "searchable": 1,
            "changeable": 1,
            "api": "csp_AppGet",
            "ext": {
                "host": "https://jingyu4k-1312635929.cos.ap-nanjing.myqcloud.com/1.json",
                "datakey": "AAdgrdghjfgswerA",
                "api": 2
            }
        },
        {
            "key": "蓝鹰影视",
            "name": "蓝鹰影视｜APP",
            "type": 3,
            "searchable": 1,
            "changeable": 1,
            "api": "csp_AppGet",
            "style": {
                "type": "rect",
                "ratio": 1.567
            },
            "ext": {
                "host": "https://lanyinghz.oss-cn-hangzhou.aliyuncs.com/lanyingxmy.txt",
                "datakey": "ca94b06ca359d80e",
                "api": 2
            }
        },
        {
            "key": "TVB云播APP",
            "name": "云播影视｜APP",
            "type": 3,
            "changeable": 0,
            "api": "https://raw.githubusercontent.com/wuheng18/zy/refs/heads/master/py/Appfox.py",
            "ext": "http://app.hktvyb.cc"
        },
        {
            "key": "花柳斋fox",
            "name": "柳斋影视｜APP",
            "type": 3,
            "changeable": 0,
            "api": "./py/Appfox.py",
            "ext": {
                "host": "http://nico.oiio.fun",
                "ver": 2
            }
        },
        {
            "key": "恋鱼影视APP",
            "name": "恋鱼影视｜APP",
            "type": 3,
            "changeable": 0,
            "api": "https://raw.githubusercontent.com/wuheng18/zy/refs/heads/master/py/Appfox.py",
            "ext": {
                "host": "http://14.103.245.78:1433",
                "parse": {
                    "去插播": "http://jerryhtom.cn/api/?key=6fo7lAFwEIjnXmhR6P&url=",
                    "官方解析": "https://www.wuyanzu.xyz/api.php?url=",
                    "JL4K": "http://118.190.204.48:99/api.php/?key=i17naujy9h&url="
                }
            }
        },
        {
            "key": "快映影视APP",
            "name": "快映影视｜APP",
            "type": 3,
            "changeable": 0,
            "api": "https://raw.githubusercontent.com/wuheng18/zy/refs/heads/master/py/Appfox.py",
            "ext": {
                "host": "https://pjb777.top/ky268.json",
                "JL4K": "http://118.190.204.48:99/api.php/?key=c0k76gjpm2&url=",
                "ver": 2
            }
        },
        {
            "key": "火猫影视APP",
            "name": "火猫影视｜APP",
            "type": 3,
            "changeable": 0,
            "api": "assets://xiaobai/xb/py/Appfox.py",
            "ext": {
                "host": "https://cunchu8.obs.cn-north-4.myhuaweicloud.com/config.json",
                "parse": {
                    "JL4K": "http://194.147.100.155:7891/?url="
                }
            }
        },
        {
            "key": "未来影视",
            "name": "未来影视｜APP",
            "type": 3,
            "changeable": 0,
            "api": "assets://xiaobai/xb/py/Appfox.py",
            "ext": {
                "host": "http://kumiao.yzbao.com.cn",
                "parse": {
                    "qq|qiyi|mgtv|youku|bilibili": "https://api.qljson.xyz/api/?key=67f6a108dc6d84eaf81ac58417c1f72a&url="
                },
                "ver": 2
            }
        },
        {
            "key": "狂人",
            "name": "狂人影视｜APP",
            "type": 3,
            "quickSearch": 1,
            "api": "assets://xiaobai/xb/py/getapp模板.py",
            "ext": {
                "host": "https://www.zjkrmv.vip",
                "datakey": "vXeyuJFqTKqWUtWU"
            }
        },
        {
            "key": "囧次元动漫",
            "name": "囧囧影视｜APP",
            "type": 3,
            "searchable": 1,
            "changeable": 1,
            "api": "csp_AppGet",
            "ext": {
                "host": "http://ys.xiaos12.cn",
                "datakey": "chfgjfrhhf628vw1"
            }
        },
        {
            "key": "番薯动漫",
            "name": "番薯影视｜APP",
            "type": 3,
            "searchable": 1,
            "changeable": 1,
            "api": "csp_AppGet",
            "ext": {
                "host": "https://new.app.bytegooty.com",
                "datakey": "N4yj7l7xKxHF4*gz"
            }
        },
        {
            "key": "mifun",
            "name": "米发影视｜APP",
            "type": 3,
            "searchable": 1,
            "changeable": 1,
            "api": "csp_AppGet",
            "ext": {
                "host": "https://miget-1313189639.cos.ap-guangzhou.myqcloud.com/mifun.txt",
                "datakey": "GETMIFUNGEIMIFUN"
            }
        },
        {
            "key": "王子TV",
            "name": "王子影视｜APP",
            "type": 3,
            "searchable": 1,
            "changeable": 1,
            "api": "csp_AppGet",
            "ext": {
                "host": "https://a41d5d4xc12c.038830.xyz/",
                "datakey": "5a9w6x58dsq6z3a6"
            }
        },
        {
            "key": "布雷4K",
            "name": "布雷影视｜APP",
            "type": 3,
            "searchable": 1,
            "changeable": 1,
            "api": "csp_AppGet",
            "ext": {
                "host": "https://ceshi307386.oss-cn-beijing.aliyuncs.com/blurl.txt",
                "datakey": "5f2b7ed203a3a581",
                "api": 2
            }
        },
        {
            "key": "nmtv",
            "name": "尼玛影视｜APP",
            "type": 3,
            "searchable": 1,
            "changeable": 1,
            "api": "csp_AppGet",
            "ext": {
                "host": "http://45.207.212.137:1008",
                "datakey": "a006661b01bdebbd"
            }
        },
        {
            "key": "云云",
            "name": "云云影视｜APP",
            "type": 3,
            "searchable": 1,
            "changeable": 1,
            "api": "csp_AppGet",
            "ext": {
                "host": "https://staraugust123456.oss-cn-hangzhou.aliyuncs.com/2.txt",
                "datakey": "staraugust123456",
                "api": 2
            }
        },
        {
            "key": "爱盈",
            "name": "爱盈影视｜APP",
            "type": 3,
            "searchable": 1,
            "changeable": 1,
            "api": "csp_AppGet",
            "ext": {
                "host": "https://aysappto.oss-cn-chengdu.aliyuncs.com/qj2.txt",
                "datakey": "sada21321sdq231d",
                "ua": "okhttp/3.10.0",
                "api": 2
            }
        },
        {
            "key": "八天App",
            "name": "八天影视｜APP",
            "type": 3,
            "searchable": 1,
            "changeable": 1,
            "api": "csp_AppGet",
            "ext": {
                "host": "https://dy.8ttv.cn/",
                "datakey": "1111111111111111"
            }
        },
        {
            "key": "次元方舟",
            "name": "方舟影视｜APP",
            "type": 3,
            "searchable": 1,
            "changeable": 1,
            "api": "csp_AppGet",
            "ext": {
                "host": "https://www.cyfz.vip",
                "datakey": "e72cdfd629e8895d"
            }
        },
        {
            "key": "D8",
            "name": "迪吧影视｜APP",
            "type": 3,
            "searchable": 1,
            "changeable": 1,
            "api": "csp_AppGet",
            "ext": {
                "host": "https://appto2-1316376600.cos.ap-beijing.myqcloud.com/appto.txt",
                "datakey": "685bf108bc47b67d"
            }
        },
        {
            "key": "猫眼影视",
            "name": "猫眼影视｜APP",
            "type": 3,
            "searchable": 1,
            "api": "csp_AppGet",
            "filterable": 1,
            "ext": {
                "host": "http://192.227.153.11",
                "datakey": "1234567890123456"
            }
        },
        {
            "key": "万能影院",
            "name": "万能影视｜APP",
            "type": 3,
            "searchable": 1,
            "api": "csp_AppGet",
            "filterable": 1,
            "ext": {
                "host": "https://wnvod.cc/",
                "datakey": "5uBvur6znNUmE3zb",
                "ua": "myapp/1.0.3"
            }
        },
        {
            "key": "坚果影视",
            "name": "坚果影视｜APP",
            "type": 3,
            "searchable": 1,
            "api": "csp_AppGet",
            "filterable": 1,
            "ext": {
                "host": "http://a.ngdy1.cn/",
                "datakey": "2015692015692015"
            }
        },
        {
            "key": "悟界影视",
            "name": "悟界影视｜APP",
            "type": 3,
            "searchable": 1,
            "api": "csp_AppGet",
            "filterable": 1,
            "ext": {
                "host": "https://tv.wjshub.cn/",
                "datakey": "qazwsxedc1234567"
            }
        },
        {
            "key": "新橘子",
            "name": "橘子影视｜APP",
            "type": 3,
            "api": "csp_AppMuou",
            "searchable": 1,
            "changeable": 1,
            "ext": {
                "host": "https://muouapp.oss-cn-hangzhou.aliyuncs.com/MUOUAPP/1687532407.txt",
                "name": "新橘子影视",
                "version": "4.2.0"
            }
        },
        {
            "key": "金牌影院",
            "name": "金牌影视｜APP",
            "type": 3,
            "api": "csp_AppMuou",
            "searchable": 1,
            "changeable": 1,
            "ext": {
                "host": "https://muouapp.oss-cn-hangzhou.aliyuncs.com/MUOUAPP/godbbq.txt",
                "name": "金牌影院（请断网再安装）",
                "version": "4.2.0"
            }
        },
        {
            "key": "csp_Guazi",
            "name": "瓜子优质｜APP",
            "type": 3,
            "api": "csp_Guazi",
            "searchable": 1,
            "changeable": 1
        },
        {
            "key": "360资源",
            "name": "360资源",
            "type": 1,
            "api": "https://360zy.com/api.php/provide/vod",
            "searchable": 1,
            "quickSearch": 1,
            "filterable": 1
        },
        {
            "key": "暴风资源",
            "name": "暴风资源",
            "type": 1,
            "api": "https://bfzyapi.com/api.php/provide/vod",
            "searchable": 1,
            "quickSearch": 1,
            "filterable": 1
        },
        {
            "key": "非凡资源",
            "name": "非凡资源",
            "type": 1,
            "api": "http://cj.ffzyapi.com/api.php/provide/vod/at/xml",
            "searchable": 1,
            "quickSearch": 1,
            "filterable": 1
        },
        {
            "key": "量子资源",
            "name": "量子资源",
            "type": 1,
            "api": "http://cj.lziapi.com/api.php/provide/vod/from/lzm3u8",
            "searchable": 1,
            "quickSearch": 1,
            "filterable": 1
        },
        {
            "key": "索尼资源采集",
            "name": "索尼",
            "type": 1,
            "api": "https://suoniapi.com/api.php/provide/vod/?ac=list",
            "searchable": 1,
            "quickSearch": 1,
            "filterable": 1,
            "changeable": 1
        },
        {
            "key": "牛牛视频",
            "name": "牛牛视频",
            "type": 1,
            "api": "https://api.niuniuzy.me/api.php/provide/vod",
            "searchable": 1,
            "quickSearch": 1,
            "filterable": 1,
            "changeable": 1
        },
        {
            "key": "最大资源",
            "name": "最大资源",
            "type": 1,
            "api": "http://zuidazy.me/api.php/provide/vod",
            "searchable": 1,
            "quickSearch": 1,
            "filterable": 1,
            "changeable": 1
        },
        {
            "key": "丫丫资源",
            "name": "丫丫资源",
            "type": 1,
            "api": "https://cj.yayazy.net/api.php/provide/vod",
            "searchable": 1,
            "quickSearch": 1,
            "filterable": 1,
            "changeable": 1
        },
        {
            "key": "茅台资源",
            "name": "茅台资源",
            "type": 1,
            "api": "https://caiji.maotaizy.cc/api.php/provide/vod/at/josn",
            "searchable": 1,
            "quickSearch": 1,
            "filterable": 1,
            "changeable": 1
        },
        {
            "key": "金鹰资源",
            "name": "金鹰资源",
            "type": 1,
            "api": "https://jyzyapi.com/provide/vod/from/jinyingm3u8",
            "searchable": 1,
            "quickSearch": 1,
            "filterable": 1,
            "changeable": 1
        },
        {
            "key": "樱花资源",
            "name": "樱花资源",
            "type": 1,
            "api": "http://m3u8.apiyhzy.com/api.php/provide/vod",
            "searchable": 1,
            "quickSearch": 1,
            "filterable": 1,
            "changeable": 1
        },
        {
            "key": "旺旺短剧",
            "name": "旺旺短剧",
            "type": 1,
            "api": "https://wwzy.tv/api.php/provide/vod",
            "searchable": 1,
            "quickSearch": 1,
            "filterable": 1
        },
        {
            "key": "天翼资源",
            "name": "天翼资源",
            "type": 1,
            "api": "https://www.911ysw.top/tianyi.php/provide/vod",
            "searchable": 1,
            "quickSearch": 1,
            "filterable": 1
        },
        {
            "key": "爱奇艺资源",
            "name": "爱奇艺资源",
            "type": 1,
            "api": "https://iqiyizyapi.com/api.php/provide/vod",
            "searchable": 1,
            "quickSearch": 1,
            "filterable": 1
        },
        {
            "key": "飘零影院",
            "name": "飘零影院",
            "type": 1,
            "api": "https://p2100.net/api.php/provide/vod",
            "searchable": 1,
            "quickSearch": 1,
            "filterable": 1
        },
        {
            "key": "极速资源",
            "name": "极速资源",
            "type": 1,
            "api": "https://jszyapi.com/api.php/provide/vod/at/json",
            "searchable": 1,
            "quickSearch": 1,
            "filterable": 1
        },
        {
            "key": "1080资源",
            "name": "1080资源",
            "type": 1,
            "api": "http://api.1080zyku.com/inc/api.php/provide/vod",
            "searchable": 1,
            "quickSearch": 1,
            "filterable": 1
        },
        {
            "key": "卧龙资源",
            "name": "卧龙资源",
            "type": 1,
            "api": "http://collect.wolongzyw.com/api.php/provide/vod",
            "searchable": 1,
            "quickSearch": 1,
            "filterable": 1
        },
        {
            "key": "电影天堂",
            "name": "电影天堂",
            "type": 1,
            "api": "http://caiji.dyttzyapi.com/api.php/provide/vod/at/xml",
            "searchable": 1,
            "quickSearch": 1,
            "filterable": 1
        },
        {
            "key": "天涯影视",
            "name": "天涯影视",
            "type": 1,
            "api": "https://tyyszyapi.com/api.php/provide/vod",
            "searchable": 1,
            "quickSearch": 1,
            "filterable": 1
        },
        {
            "key": "光速资源",
            "name": "光速资源",
            "type": 1,
            "api": "https://api.guangsuapi.com/api.php/provide/vod/from/gsm3u8",
            "searchable": 1,
            "quickSearch": 1,
            "filterable": 1
        },
        {
            "key": "百度资源",
            "name": "百度资源",
            "type": 1,
            "api": "http://api.apibdzy.com/api.php/provide/vod",
            "searchable": 1,
            "quickSearch": 1,
            "filterable": 1
        },
        {
            "key": "魔都资源",
            "name": "魔都资源",
            "type": 1,
            "api": "https://www.mdzyapi.com/api.php/provide/vod",
            "searchable": 1,
            "quickSearch": 1,
            "filterable": 1
        },
        {
            "key": "豆瓣资源",
            "name": "豆瓣资源",
            "type": 1,
            "api": "https://caiji.dbzy5.com/api.php/provide/vod/at/josn",
            "searchable": 1,
            "quickSearch": 1,
            "filterable": 1
        },
        {
            "key": "猫眼资源",
            "name": "猫眼资源",
            "type": 1,
            "api": "https://api.maoyanapi.top/api.php/provide/vod",
            "searchable": 1,
            "quickSearch": 1,
            "filterable": 1
        },
        {
            "key": "闪电资源",
            "name": "闪电资源",
            "type": 1,
            "api": "http://sdzyapi.com/api.php/provide/vod/from/sdm3u8",
            "searchable": 1,
            "quickSearch": 1,
            "filterable": 1
        },
        {
            "key": "红牛资源",
            "name": "红牛资源",
            "type": 1,
            "api": "http://hongniuzy2.com/api.php/provide/vod/from/hnm3u8",
            "searchable": 1,
            "quickSearch": 1,
            "filterable": 1
        },
        {
            "key": "速播资源",
            "name": "速播资源",
            "type": 1,
            "api": "https://subocj.com/api.php/provide/vod/at/json",
            "searchable": 1,
            "quickSearch": 1,
            "filterable": 1
        }
    ]
}